dj_generator/__init__.py
dj_generator/admin.py
dj_generator/apps.py
dj_generator/management/commands/_private.py
dj_generator/management/commands/generate.py
dj_generator/migrations/__init__.py
dj_generator/models.py
dj_generator/templates/dj_generator/curd/default/code/urls.py
dj_generator/templates/dj_generator/curd/default/code/views.py
dj_generator/templates/dj_generator/curd/default/templates/create.html
dj_generator/templates/dj_generator/curd/default/templates/delete_confirm.html
dj_generator/templates/dj_generator/curd/default/templates/detail.html
dj_generator/templates/dj_generator/curd/default/templates/list.html
dj_generator/templates/dj_generator/curd/default/templates/update.html
dj_generator/templates/dj_generator/curd/power/code/forms.py
dj_generator/templates/dj_generator/curd/power/code/table.py
dj_generator/templates/dj_generator/curd/power/code/urls.py
dj_generator/templates/dj_generator/curd/power/code/views.py
dj_generator/templates/dj_generator/curd/power/templates/create.html
dj_generator/templates/dj_generator/curd/power/templates/delete_confirm.html
dj_generator/templates/dj_generator/curd/power/templates/detail.html
dj_generator/templates/dj_generator/curd/power/templates/list.html
dj_generator/templates/dj_generator/curd/power/templates/table_actions.html
dj_generator/templates/dj_generator/curd/power/templates/update.html
dj_generator/templatetags/__init__.py
dj_generator/templatetags/generator_tags.py
dj_generator/tests.py
dj_generator/views.py
dj_generator-0.0.1.dist-info/WHEEL
dj_generator-0.0.1.dist-info/METADATA
dj_generator-0.0.1.dist-info/RECORD
