Metadata-Version: 2.1
Name: dj-generator
Version: 0.0.1
Summary: Boilerplate generator for django
Home-page: https://github.com/shimulch/dj-generator
License: MIT
Keywords: django,crud,crud-generator,generator
Author: Shimul Chowdhury
Author-email: shimul@divine-it.net
Requires-Python: >=3.6,<4.0
Classifier: Intended Audience :: Developers
Classifier: License :: OSI Approved :: MIT License
Classifier: Programming Language :: Python :: 3
Classifier: Programming Language :: Python :: 3.6
Classifier: Programming Language :: Python :: 3.7
Classifier: Programming Language :: Python :: 3.8
Classifier: Programming Language :: Python :: Implementation :: PyPy
Classifier: Topic :: Software Development :: Libraries
Requires-Dist: django (>=3.0.5,<4.0.0)
Project-URL: Repository, https://github.com/shimulch/dj-generator
